printmoji/__init__.py
printmoji-1.0.0.dist-info/METADATA
printmoji-1.0.0.dist-info/WHEEL
printmoji-1.0.0.dist-info/top_level.txt
printmoji-1.0.0.dist-info/RECORD
