Metadata-Version: 2.1
Name: printmoji
Version: 1.0.0
Summary: Printing with emojis
Author: Kyle Williams
Classifier: Operating System :: POSIX :: Linux
Classifier: Operating System :: Microsoft :: Windows
Classifier: Programming Language :: Python :: 3
Requires-Python: >=3
